fastapi_authix/__init__.py
fastapi_authix/exceptions.py
fastapi_authix/serializers.py
fastapi_authix/typing.py
fastapi_authix/vault.py
fastapi_authix/security/__init__.py
fastapi_authix/security/fernet.py
fastapi_authix/security/protocol.py
fastapi_authix-0.1.0.dist-info/METADATA
fastapi_authix-0.1.0.dist-info/WHEEL
fastapi_authix-0.1.0.dist-info/licenses/LICENSE
fastapi_authix-0.1.0.dist-info/RECORD
